topdrawersoccer_sdk/__init__.py
topdrawersoccer_sdk/conference.py
topdrawersoccer_sdk/constants.py
topdrawersoccer_sdk/mapping.py
topdrawersoccer_sdk/utils.py
topdrawersoccer_sdk/page/__init__.py
topdrawersoccer_sdk/page/club.py
topdrawersoccer_sdk/page/coach.py
topdrawersoccer_sdk/page/college.py
topdrawersoccer_sdk/page/conference.py
topdrawersoccer_sdk/page/config.py
topdrawersoccer_sdk/page/player.py
topdrawersoccer_sdk/page/team.py
topdrawersoccer_sdk/page/transfers.py
topdrawersoccer_sdk-0.1.1.dist-info/METADATA
topdrawersoccer_sdk-0.1.1.dist-info/WHEEL
topdrawersoccer_sdk-0.1.1.dist-info/top_level.txt
topdrawersoccer_sdk-0.1.1.dist-info/RECORD
